{
    "datas": [
        {
            "children": [
                {
                    "name": "小米"
                },
                {
                    "name": "苹果"
                },
                {
                    "name": "华为"
                },
                {
                    "name": "联想"
                },
                {
                    "name": "联想"
                },
                {
                    "name": "联想"
                },
                {
                    "name": "联想"
                },
                {
                    "name": "联想"
                },
                {
                    "name": "联想"
                },
                {
                    "name": "联想"
                },
                {
                    "name": "联想"
                },
                {
                    "name": "联想"
                },
                {
                    "name": "联想"
                },
                {
                    "name": "联想"
                },
                {
                    "name": "联想"
                },
                {
                    "name": "联想"
                }
            ]
        }
    ]
}